Metadata-Version: 2.4
Name: django-orm-to-excel
Version: 2.1.7
Summary: Turning Django ORM objects to Excel
Requires-Python: >=3.9
Requires-Dist: jinja2==3.1.6
Requires-Dist: openpyxl==3.1.5
